dcaf/__init__.py
dcaf/agent_server.py
dcaf/channel_routing.py
dcaf/cli.py
dcaf/tools.py
dcaf/agents/__init__.py
dcaf/agents/aws_agent.py
dcaf/agents/boilerplate_agent.py
dcaf/agents/cmd_agent.py
dcaf/agents/echo_agent.py
dcaf/agents/k8s_agent.py
dcaf/agents/llm_passthrough_agent.py
dcaf/agents/tool_calling_agent.py
dcaf/agents/tool_calling_agent_boilerplate.py
dcaf/agents/tool_calling_cmd_agent.py
dcaf/llm/__init__.py
dcaf/llm/base.py
dcaf/llm/bedrock.py
dcaf/schemas/__init__.py
dcaf/schemas/events.py
dcaf/schemas/messages.py
duplo_dcaf-0.0.1.dist-info/licenses/LICENSE
duplo_dcaf-0.0.1.dist-info/METADATA
duplo_dcaf-0.0.1.dist-info/WHEEL
duplo_dcaf-0.0.1.dist-info/entry_points.txt
duplo_dcaf-0.0.1.dist-info/top_level.txt
duplo_dcaf-0.0.1.dist-info/RECORD
