Metadata-Version: 2.4
Name: duplo-dcaf
Version: 0.0.1
Summary: DuploCloud Agent Builder (DAB) - A framework for building LLM powered AI agents and workflows that integrate with the DuploCloud Help Desk.
Author-email: DuploCloud <support@duplocloud.com>
License: MIT
Project-URL: Homepage, https://github.com/duplocloud/service-desk-agents/tree/pip-package
Keywords: ai,agents,duplocloud,chatbot,llm
Classifier: Development Status :: 3 - Alpha
Classifier: Intended Audience :: Developers
Classifier: License :: OSI Approved :: MIT License
Classifier: Programming Language :: Python :: 3
Classifier: Programming Language :: Python :: 3.9
Classifier: Programming Language :: Python :: 3.10
Classifier: Programming Language :: Python :: 3.11
Classifier: Programming Language :: Python :: 3.12
Classifier: Programming Language :: Python :: 3.13
Classifier: Topic :: Software Development :: Libraries :: Python Modules
Classifier: Topic :: Scientific/Engineering :: Artificial Intelligence
Requires-Python: >=3.9
License-File: LICENSE
Requires-Dist: fastapi
Requires-Dist: pydantic
Requires-Dist: uvicorn
Requires-Dist: boto3
Requires-Dist: python-dotenv
Requires-Dist: tk
Requires-Dist: requests
Requires-Dist: langchain_community
Requires-Dist: duplocloud-client
Dynamic: license-file
